[
  {
    "rank": 1,
    "username": "notalama",
    "link": "https://vndb.org/u24837",
    "jizzat": 82414
  },
  {
    "rank": 2,
    "username": "spiegelspike",
    "link": "https://vndb.org/u160213",
    "jizzat": 76767
  },
  {
    "rank": 3,
    "username": "clephas",
    "link": "https://vndb.org/u10917",
    "jizzat": 75275
  },
  {
    "rank": 4,
    "username": "hutami",
    "link": "https://vndb.org/u135107",
    "jizzat": 73563
  },
  {
    "rank": 5,
    "username": "Grimlock",
    "link": "https://vndb.org/u286850",
    "jizzat": 72494
  },
  {
    "rank": 6,
    "username": "hasegawamanatsu",
    "link": "https://vndb.org/u119921",
    "jizzat": 72008
  },
  {
    "rank": 7,
    "username": "ttm",
    "link": "https://vndb.org/u117174",
    "jizzat": 69287
  },
  {
    "rank": 8,
    "username": "ever",
    "link": "https://vndb.org/u181274",
    "jizzat": 69060
  },
  {
    "rank": 9,
    "username": "fale",
    "link": "https://vndb.org/u164918",
    "jizzat": 65936
  },
  {
    "rank": 10,
    "username": "indragp136",
    "link": "https://vndb.org/u24410",
    "jizzat": 65070
  },
  {
    "rank": 11,
    "username": "Saltron",
    "link": "https://vndb.org/u206735",
    "jizzat": 64154
  },
  {
    "rank": 12,
    "username": "unico",
    "link": "https://vndb.org/u23992",
    "jizzat": 63661
  },
  {
    "rank": 13,
    "username": "killarun4",
    "link": "https://vndb.org/u3403",
    "jizzat": 61053
  },
  {
    "rank": 14,
    "username": "ryudo045",
    "link": "https://vndb.org/u204910",
    "jizzat": 60623
  },
  {
    "rank": 15,
    "username": "johnyb",
    "link": "https://vndb.org/u22539",
    "jizzat": 58364
  },
  {
    "rank": 16,
    "username": "h1kari",
    "link": "https://vndb.org/u104685",
    "jizzat": 58107
  },
  {
    "rank": 17,
    "username": "kaorukamio",
    "link": "https://vndb.org/u198224",
    "jizzat": 56993
  },
  {
    "rank": 18,
    "username": "bilal",
    "link": "https://vndb.org/u116692",
    "jizzat": 56555
  },
  {
    "rank": 19,
    "username": "Kasane0933",
    "link": "https://vndb.org/u226280",
    "jizzat": 54882
  },
  {
    "rank": 20,
    "username": "DGx8",
    "link": "https://vndb.org/u87351",
    "jizzat": 53277
  },
  {
    "rank": 21,
    "username": "SakuragiMizuha",
    "link": "https://vndb.org/u192993",
    "jizzat": 52443
  },
  {
    "rank": 22,
    "username": "rarepotato",
    "link": "https://vndb.org/u143559",
    "jizzat": 51568
  },
  {
    "rank": 23,
    "username": "AmanoKaze",
    "link": "https://vndb.org/u63229",
    "jizzat": 51211
  },
  {
    "rank": 24,
    "username": "tailtale13",
    "link": "https://vndb.org/u76127",
    "jizzat": 51102
  },
  {
    "rank": 25,
    "username": "blane",
    "link": "https://vndb.org/u54937",
    "jizzat": 50787
  },
  {
    "rank": 26,
    "username": "tyrog",
    "link": "https://vndb.org/u116458",
    "jizzat": 50530
  },
  {
    "rank": 27,
    "username": "WatsonChao",
    "link": "https://vndb.org/u248014",
    "jizzat": 50404
  },
  {
    "rank": 28,
    "username": "alexlung",
    "link": "https://vndb.org/u80410",
    "jizzat": 50333
  },
  {
    "rank": 29,
    "username": "mashiro1388",
    "link": "https://vndb.org/u258119",
    "jizzat": 49619
  },
  {
    "rank": 30,
    "username": "hadler",
    "link": "https://vndb.org/u12472",
    "jizzat": 49390
  },
  {
    "rank": 31,
    "username": "resona",
    "link": "https://vndb.org/u124557",
    "jizzat": 48976
  },
  {
    "rank": 32,
    "username": "cless",
    "link": "https://vndb.org/u1825",
    "jizzat": 48721
  },
  {
    "rank": 33,
    "username": "dartprince",
    "link": "https://vndb.org/u5678",
    "jizzat": 48380
  },
  {
    "rank": 34,
    "username": "necrofantasia",
    "link": "https://vndb.org/u77155",
    "jizzat": 47296
  },
  {
    "rank": 35,
    "username": "rimvydasm",
    "link": "https://vndb.org/u108164",
    "jizzat": 47199
  },
  {
    "rank": 36,
    "username": "loss",
    "link": "https://vndb.org/u336",
    "jizzat": 47153
  },
  {
    "rank": 37,
    "username": "kato2751",
    "link": "https://vndb.org/u206186",
    "jizzat": 47032
  },
  {
    "rank": 38,
    "username": "nidhogg-as",
    "link": "https://vndb.org/u169312",
    "jizzat": 46355
  },
  {
    "rank": 39,
    "username": "Limz",
    "link": "https://vndb.org/u255681",
    "jizzat": 45759
  },
  {
    "rank": 40,
    "username": "steven2209",
    "link": "https://vndb.org/u75251",
    "jizzat": 45446
  },
  {
    "rank": 41,
    "username": "kanatadesu",
    "link": "https://vndb.org/u213971",
    "jizzat": 45072
  },
  {
    "rank": 42,
    "username": "asakurajun",
    "link": "https://vndb.org/u37836",
    "jizzat": 43939
  },
  {
    "rank": 43,
    "username": "ding1997",
    "link": "https://vndb.org/u123383",
    "jizzat": 43033
  },
  {
    "rank": 44,
    "username": "djksl",
    "link": "https://vndb.org/u183348",
    "jizzat": 42776
  },
  {
    "rank": 45,
    "username": "bdawg",
    "link": "https://vndb.org/u50636",
    "jizzat": 42184
  },
  {
    "rank": 46,
    "username": "Uzako",
    "link": "https://vndb.org/u84373",
    "jizzat": 41981
  },
  {
    "rank": 47,
    "username": "stanleykur",
    "link": "https://vndb.org/u34172",
    "jizzat": 40088
  },
  {
    "rank": 48,
    "username": "harrymahar",
    "link": "https://vndb.org/u26123",
    "jizzat": 39511
  },
  {
    "rank": 49,
    "username": "seshio",
    "link": "https://vndb.org/u157528",
    "jizzat": 39307
  },
  {
    "rank": 50,
    "username": "fudouyusei",
    "link": "https://vndb.org/u177045",
    "jizzat": 39042
  },
  {
    "rank": 51,
    "username": "deivid1994",
    "link": "https://vndb.org/u177156",
    "jizzat": 38841
  },
  {
    "rank": 52,
    "username": "mitsukiyui95",
    "link": "https://vndb.org/u120922",
    "jizzat": 38447
  },
  {
    "rank": 53,
    "username": "z411-neptune",
    "link": "https://vndb.org/u12793",
    "jizzat": 38094
  },
  {
    "rank": 54,
    "username": "kumiko1",
    "link": "https://vndb.org/u128536",
    "jizzat": 38023
  },
  {
    "rank": 55,
    "username": "desserter",
    "link": "https://vndb.org/u3374",
    "jizzat": 38013
  },
  {
    "rank": 56,
    "username": "infinitylunhui",
    "link": "https://vndb.org/u137686",
    "jizzat": 37617
  },
  {
    "rank": 57,
    "username": "davidlu9837",
    "link": "https://vndb.org/u1177",
    "jizzat": 37606
  },
  {
    "rank": 58,
    "username": "craiven",
    "link": "https://vndb.org/u147173",
    "jizzat": 37297
  },
  {
    "rank": 59,
    "username": "ericj240691",
    "link": "https://vndb.org/u25939",
    "jizzat": 37005
  },
  {
    "rank": 60,
    "username": "teioh",
    "link": "https://vndb.org/u45347",
    "jizzat": 36401
  },
  {
    "rank": 61,
    "username": "ChrisY9",
    "link": "https://vndb.org/u221431",
    "jizzat": 35905
  },
  {
    "rank": 62,
    "username": "wachaii",
    "link": "https://vndb.org/u306231",
    "jizzat": 35560
  },
  {
    "rank": 63,
    "username": "shangzuimeng",
    "link": "https://vndb.org/u228747",
    "jizzat": 35474
  },
  {
    "rank": 64,
    "username": "Yondermore",
    "link": "https://vndb.org/u288581",
    "jizzat": 35395
  },
  {
    "rank": 65,
    "username": "nigriel",
    "link": "https://vndb.org/u3320",
    "jizzat": 35306
  },
  {
    "rank": 66,
    "username": "kohntarkosz",
    "link": "https://vndb.org/u33031",
    "jizzat": 34981
  },
  {
    "rank": 67,
    "username": "desann",
    "link": "https://vndb.org/u2682",
    "jizzat": 34687
  },
  {
    "rank": 68,
    "username": "haruhiai",
    "link": "https://vndb.org/u271518",
    "jizzat": 34510
  },
  {
    "rank": 69,
    "username": "lodadx",
    "link": "https://vndb.org/u120710",
    "jizzat": 33957
  },
  {
    "rank": 70,
    "username": "usuisorata",
    "link": "https://vndb.org/u155786",
    "jizzat": 33878
  },
  {
    "rank": 71,
    "username": "lilylvl",
    "link": "https://vndb.org/u294099",
    "jizzat": 33155
  },
  {
    "rank": 72,
    "username": "demlune",
    "link": "https://vndb.org/u20220",
    "jizzat": 33147
  },
  {
    "rank": 73,
    "username": "pottmill",
    "link": "https://vndb.org/u229078",
    "jizzat": 32851
  },
  {
    "rank": 74,
    "username": "MikoMeteorite",
    "link": "https://vndb.org/u248035",
    "jizzat": 32730
  },
  {
    "rank": 75,
    "username": "bxaxkxa",
    "link": "https://vndb.org/u157834",
    "jizzat": 32662
  },
  {
    "rank": 76,
    "username": "repiphany",
    "link": "https://vndb.org/u28206",
    "jizzat": 32662
  },
  {
    "rank": 77,
    "username": "kechi",
    "link": "https://vndb.org/u217566",
    "jizzat": 32572
  },
  {
    "rank": 78,
    "username": "naximier46",
    "link": "https://vndb.org/u82382",
    "jizzat": 32419
  },
  {
    "rank": 79,
    "username": "minato-tomoka",
    "link": "https://vndb.org/u215782",
    "jizzat": 32383
  },
  {
    "rank": 80,
    "username": "watchmanx",
    "link": "https://vndb.org/u144003",
    "jizzat": 32337
  },
  {
    "rank": 81,
    "username": "tendays",
    "link": "https://vndb.org/u175426",
    "jizzat": 32261
  },
  {
    "rank": 82,
    "username": "onorub",
    "link": "https://vndb.org/u135571",
    "jizzat": 31632
  },
  {
    "rank": 83,
    "username": "TuruTime",
    "link": "https://vndb.org/u164828",
    "jizzat": 31557
  },
  {
    "rank": 84,
    "username": "leonnagakemi",
    "link": "https://vndb.org/u59826",
    "jizzat": 31512
  },
  {
    "rank": 85,
    "username": "Karbic",
    "link": "https://vndb.org/u276603",
    "jizzat": 31396
  },
  {
    "rank": 86,
    "username": "cyberloli",
    "link": "https://vndb.org/u4148",
    "jizzat": 31319
  },
  {
    "rank": 87,
    "username": "liblume",
    "link": "https://vndb.org/u162329",
    "jizzat": 31266
  },
  {
    "rank": 88,
    "username": "mikesarat",
    "link": "https://vndb.org/u123335",
    "jizzat": 31090
  },
  {
    "rank": 89,
    "username": "HakuRyuu",
    "link": "https://vndb.org/u137826",
    "jizzat": 31082
  },
  {
    "rank": 90,
    "username": "ranzkin",
    "link": "https://vndb.org/u15505",
    "jizzat": 31056
  },
  {
    "rank": 91,
    "username": "allamsct",
    "link": "https://vndb.org/u34899",
    "jizzat": 31024
  },
  {
    "rank": 92,
    "username": "Myaa",
    "link": "https://vndb.org/u137268",
    "jizzat": 30959
  },
  {
    "rank": 93,
    "username": "thndrchs",
    "link": "https://vndb.org/u910",
    "jizzat": 30828
  },
  {
    "rank": 94,
    "username": "deadpan",
    "link": "https://vndb.org/u92176",
    "jizzat": 30794
  },
  {
    "rank": 95,
    "username": "el-ahrairah",
    "link": "https://vndb.org/u184179",
    "jizzat": 30780
  },
  {
    "rank": 96,
    "username": "Raien",
    "link": "https://vndb.org/u144864",
    "jizzat": 30675
  },
  {
    "rank": 97,
    "username": "sakuraho",
    "link": "https://vndb.org/u273562",
    "jizzat": 30612
  },
  {
    "rank": 98,
    "username": "skr-natsume",
    "link": "https://vndb.org/u189446",
    "jizzat": 30594
  },
  {
    "rank": 99,
    "username": "nacyu",
    "link": "https://vndb.org/u168109",
    "jizzat": 30582
  },
  {
    "rank": 100,
    "username": "fureiyus",
    "link": "https://vndb.org/u84342",
    "jizzat": 30480
  }
]